glamkit_sponsors-0.5.dist-info/DESCRIPTION.rst
glamkit_sponsors-0.5.dist-info/METADATA
glamkit_sponsors-0.5.dist-info/metadata.json
glamkit_sponsors-0.5.dist-info/RECORD
glamkit_sponsors-0.5.dist-info/top_level.txt
glamkit_sponsors-0.5.dist-info/WHEEL
sponsors/__init__.py
sponsors/admin.py
sponsors/apps.py
sponsors/content_plugins.py
sponsors/models.py
sponsors/migrations/0001_initial.py
sponsors/migrations/0002_beginsponsorblockitem_endsponsorblockitem_sponsorpromoitem.py
sponsors/migrations/__init__.py
sponsors/templates/plugins/sponsor_block/begin.html
sponsors/templates/plugins/sponsor_block/end.html
sponsors/templates/plugins/sponsor_block/sponsor.html
